django_calendards/__init__.py
django_calendards/admin.py
django_calendards/apps.py
django_calendards/models.py
django_calendards/tests.py
django_calendards/views.py
django_calendards/migrations/0001_initial.py
django_calendards/migrations/__init__.py
django_calendards/static/calendards/fullcalendar4/packages/bootstrap/LICENSE.txt
django_calendards/static/calendards/fullcalendar4/packages/bootstrap/README.md
django_calendards/static/calendards/fullcalendar4/packages/bootstrap/main.css
django_calendards/static/calendards/fullcalendar4/packages/bootstrap/main.d.ts
django_calendards/static/calendards/fullcalendar4/packages/bootstrap/main.esm.js
django_calendards/static/calendards/fullcalendar4/packages/bootstrap/main.js
django_calendards/static/calendards/fullcalendar4/packages/bootstrap/main.min.css
django_calendards/static/calendards/fullcalendar4/packages/bootstrap/main.min.js
django_calendards/static/calendards/fullcalendar4/packages/bootstrap/package.json
django_calendards/static/calendards/fullcalendar4/packages/core/LICENSE.txt
django_calendards/static/calendards/fullcalendar4/packages/core/README.md
django_calendards/static/calendards/fullcalendar4/packages/core/locales-all.js
django_calendards/static/calendards/fullcalendar4/packages/core/locales-all.min.js
django_calendards/static/calendards/fullcalendar4/packages/core/main.css
django_calendards/static/calendards/fullcalendar4/packages/core/main.d.ts
django_calendards/static/calendards/fullcalendar4/packages/core/main.esm.js
django_calendards/static/calendards/fullcalendar4/packages/core/main.js
django_calendards/static/calendards/fullcalendar4/packages/core/main.min.css
django_calendards/static/calendards/fullcalendar4/packages/core/main.min.js
django_calendards/static/calendards/fullcalendar4/packages/core/package.json
django_calendards/static/calendards/fullcalendar4/packages/core/locales/af.js
django_calendards/static/calendards/fullcalendar4/packages/core/locales/ar-dz.js
django_calendards-0.4.2.dist-info/LICENSE
django_calendards-0.4.2.dist-info/WHEEL
django_calendards-0.4.2.dist-info/METADATA
django_calendards-0.4.2.dist-info/RECORD
